opencv_transforms/__init__.py
opencv_transforms/functional.py
opencv_transforms/transforms.py
opencv_transforms-0.0.6.dist-info/LICENSE
opencv_transforms-0.0.6.dist-info/METADATA
opencv_transforms-0.0.6.dist-info/WHEEL
opencv_transforms-0.0.6.dist-info/top_level.txt
opencv_transforms-0.0.6.dist-info/RECORD
