Metadata-Version: 2.1
Name: opencv-transforms
Version: 0.0.6
Summary: A drop-in replacement for Torchvision Transforms using OpenCV
Home-page: https://github.com/jbohnslav/opencv_transforms
Author: Jim Bohnslav
Author-email: JBohnslav@gmail.com
License: UNKNOWN
Keywords: pytorch image augmentations
Platform: UNKNOWN
Classifier: Programming Language :: Python :: 3
Classifier: License :: OSI Approved :: MIT License
Classifier: Operating System :: OS Independent
Requires-Python: >=3.6
